kg_rabbitmq/__init__.py
kg_rabbitmq/builder.py
kg_rabbitmq/configfile.py
kg_rabbitmq/option.py
kg_rabbitmq/py.typed
kg_rabbitmq/tests/__init__.py
kg_rabbitmq/tests/test_builder.py
tests/__init__.py
tests/test_builder.py
kg_rabbitmq-0.8.2.dist-info/LICENSE
kg_rabbitmq-0.8.2.dist-info/METADATA
kg_rabbitmq-0.8.2.dist-info/WHEEL
kg_rabbitmq-0.8.2.dist-info/top_level.txt
kg_rabbitmq-0.8.2.dist-info/RECORD
